dice_mc/__init__.py
dice_mc/torch.py
dice_mc/tests/__init__.py
dice_mc/tests/test_torch.py
dice_mc-0.1.1.dist-info/LICENSE
dice_mc-0.1.1.dist-info/METADATA
dice_mc-0.1.1.dist-info/NOTICE
dice_mc-0.1.1.dist-info/WHEEL
dice_mc-0.1.1.dist-info/top_level.txt
dice_mc-0.1.1.dist-info/RECORD
