Metadata-Version: 2.1
Name: dice-mc
Version: 0.1.1
Summary: DiCE: The Infinitely Differentiable Monte-Carlo Estimator
Home-page: https://github.com/crowsonkb/dice-mc
Author: Katherine Crowson
Author-email: crowsonkb@gmail.com
License: Apache-2.0
Classifier: Development Status :: 3 - Alpha
Classifier: Intended Audience :: Science/Research
Classifier: License :: OSI Approved :: Apache Software License
Classifier: Operating System :: OS Independent
Classifier: Topic :: Scientific/Engineering :: Artificial Intelligence
License-File: LICENSE
License-File: NOTICE
Requires-Dist: torch
